mem0mcp/__init__.py
mem0mcp/__main__.py
mem0mcp/server.py
mem0_mcp_for_pm-0.3.2.dist-info/METADATA
mem0_mcp_for_pm-0.3.2.dist-info/WHEEL
mem0_mcp_for_pm-0.3.2.dist-info/entry_points.txt
mem0_mcp_for_pm-0.3.2.dist-info/RECORD
