Metadata-Version: 2.4
Name: mem0-mcp-for-pm
Version: 0.3.2
Summary: MCP Server for mem0 project management integration
Project-URL: Homepage, https://github.com/KunihiroS/mem0-mcp-for-pm
Project-URL: Bug Tracker, https://github.com/KunihiroS/mem0-mcp-for-pm/issues
Author-email: Kunihiro Sugiyama <kunihiros@gmail.com>
Maintainer-email: Kunihiro Sugiyama <kunihiros@gmail.com>
Classifier: Development Status :: 3 - Alpha
Classifier: Intended Audience :: Developers
Classifier: Programming Language :: Python :: 3
Classifier: Programming Language :: Python :: 3.12
Requires-Python: >=3.12
Requires-Dist: httpx>=0.28.1
Requires-Dist: mcp>=1.6.0
Requires-Dist: mem0ai>=0.1.55
Requires-Dist: python-dotenv>=1.0.0
